README.md
setup.cfg
setup.py
mercy/__init__.py
mercy/__main__.py
mercy.egg-info/PKG-INFO
mercy.egg-info/SOURCES.txt
mercy.egg-info/dependency_links.txt
mercy.egg-info/entry_points.txt
mercy.egg-info/requires.txt
mercy.egg-info/top_level.txt
mercy.egg-info/zip-safe