Metadata-Version: 1.2
Name: mercy
Version: 0.1.0a0
Summary:  mercy - a Python 3.x web framework 
Home-page: https://github.com/LimpidTech/mercy
Author: Bailey "monokrome" Stoner
Author-email: monokrome@monokro.me
Maintainer: Bailey "monokrome" Stoner
Maintainer-email: monokrome@monokro.me
License: BSD 3-Clause License
Keywords: web,framework
Platform: UNKNOWN
Classifier: Environment :: Web Environment
Classifier: Programming Language :: Python :: 3
